fluentd_logger/__init__.py
fluentd_logger/__main__.py
fluentd_logger/cli_constants.py
fluentd_logger/env_constants.py
fluentd_logger/env_startup.py
fluentd_logger/environment.py
fluentd_logger/io_utils.py
fluentd_logger/logger.py
fluentd_logger-1.0.0.dist-info/LICENSE
fluentd_logger-1.0.0.dist-info/METADATA
fluentd_logger-1.0.0.dist-info/WHEEL
fluentd_logger-1.0.0.dist-info/top_level.txt
fluentd_logger-1.0.0.dist-info/RECORD
