Metadata-Version: 2.1
Name: fluentd-logger
Version: 1.0.0
Summary: Simple fluentd logger library
Home-page: https://github.com/estuaryoss/test-libs-python/tree/master/fluentd_logger
Author: Catalin Dinuta
Author-email: constantin.dinuta@gmail.com
License: UNKNOWN
Platform: UNKNOWN
Classifier: Programming Language :: Python :: 3.7
Classifier: Programming Language :: Python :: 3.8
Classifier: Programming Language :: Python :: 3.9
Classifier: License :: OSI Approved :: Apache Software License
Classifier: Operating System :: OS Independent
Requires-Dist: click
Requires-Dist: fluent-logger
Requires-Dist: setuptools (==44.0.0)
Requires-Dist: jproperties
